sftpwrapper/__init__.py
sftpwrapper/sftpwrapper.py
sftpwrapper-0.2.2.dist-info/LICENSE
sftpwrapper-0.2.2.dist-info/METADATA
sftpwrapper-0.2.2.dist-info/WHEEL
sftpwrapper-0.2.2.dist-info/top_level.txt
sftpwrapper-0.2.2.dist-info/RECORD
