Metadata-Version: 2.1
Name: sftpwrapper
Version: 0.2.2
Summary: A python program that facilitates uploading and downloading of files to/from an SFTP server
Home-page: UNKNOWN
Author: Kyle Wolfe
Author-email: kwolfe@northampton.edu
License: MIT
Keywords: sftp ftp
Platform: UNKNOWN
Classifier: Development Status :: 4 - Beta
Classifier: Environment :: Console
Classifier: Intended Audience :: Developers
Classifier: Programming Language :: Python
Requires-Python: >3.6
Requires-Dist: paramiko
